lark/__init__.py
lark/ast_utils.py
lark/common.py
lark/exceptions.py
lark/grammar.py
lark/indenter.py
lark/lark.py
lark/lexer.py
lark/load_grammar.py
lark/parse_tree_builder.py
lark/parser_frontends.py
lark/py.typed
lark/reconstruct.py
lark/tree.py
lark/tree_matcher.py
lark/tree_templates.py
lark/utils.py
lark/visitors.py
lark/__pyinstaller/__init__.py
lark/__pyinstaller/hook-lark.py
lark/grammars/__init__.py
lark/grammars/common.lark
lark/grammars/lark.lark
lark/grammars/python.lark
lark/grammars/unicode.lark
lark/parsers/__init__.py
lark/parsers/cyk.py
lark/parsers/earley.py
lark/parsers/earley_common.py
lark/parsers/earley_forest.py
lark/parsers/grammar_analysis.py
lark/parsers/lalr_analysis.py
lark/parsers/lalr_interactive_parser.py
lark/parsers/lalr_parser.py
lark/parsers/lalr_parser_state.py
lark/parsers/xearley.py
lark/tools/__init__.py
lark/tools/nearley.py
lark/tools/serialize.py
lark/tools/standalone.py
lark-1.2.1.dist-info/LICENSE
lark-1.2.1.dist-info/METADATA
lark-1.2.1.dist-info/WHEEL
lark-1.2.1.dist-info/entry_points.txt
lark-1.2.1.dist-info/top_level.txt
lark-1.2.1.dist-info/RECORD
