Metadata-Version: 2.1
Name: lark
Version: 1.2.1
Summary: a modern parsing library
Author-email: Erez Shinan <erezshin@gmail.com>
License: MIT
Project-URL: Homepage, https://github.com/lark-parser/lark
Project-URL: Download, https://github.com/lark-parser/lark/tarball/master
Keywords: Earley,LALR,parser,parsing,ast
Classifier: Development Status :: 5 - Production/Stable
Classifier: Intended Audience :: Developers
Classifier: Programming Language :: Python :: 3
Classifier: Topic :: Software Development :: Libraries :: Python Modules
Classifier: Topic :: Text Processing :: General
Classifier: Topic :: Text Processing :: Linguistic
Classifier: License :: OSI Approved :: MIT License
Requires-Python: >=3.8
License-File: LICENSE
Provides-Extra: atomic_cache
Requires-Dist: atomicwrites ; extra == 'atomic_cache'
Provides-Extra: interegular
Requires-Dist: interegular <0.4.0,>=0.3.1 ; extra == 'interegular'
Provides-Extra: nearley
Requires-Dist: js2py ; extra == 'nearley'
Provides-Extra: regex
Requires-Dist: regex ; extra == 'regex'
